fifo_sync.v
`timescale 1ns / 1ps
//////////////////////////////////////////////////////////////////////////////////
// Company: 
// Engineer: 
// 
// Create Date: 06/09/2025 05:50:02 PM
// Design Name: 
// Module Name: fifo_sync
// Project Name: 
// Target Devices: 
// Tool Versions: 
// Description: 
// 
// Dependencies: 
// 
// Revision:
// Revision 0.01 - File Created
// Additional Comments:
// 
//////////////////////////////////////////////////////////////////////////////////


module fifo_sync
#(
    parameter FIFO_DEPTH = 8,
    parameter DATA_WIDTH = 32
)
(
    input wire clk,
    input wire rst_n,
    input wire cs,
    input wire wr_en,
    input wire rd_en,
    input wire [DATA_WIDTH-1:0] data_in,
    output reg [DATA_WIDTH-1:0] data_out,
    output wire empty,
    output wire full
);

    localparam FIFO_DEPTH_LOG = $clog2(FIFO_DEPTH);

    // FIFO memory declaration
    reg [DATA_WIDTH-1:0] fifo [0:FIFO_DEPTH-1];

    // Read and write pointers (with wraparound logic)
    reg [FIFO_DEPTH_LOG:0] write_pointer;
    reg [FIFO_DEPTH_LOG:0] read_pointer;

    // Write operation
    always @(posedge clk or negedge rst_n) begin
        if (!rst_n) begin
            write_pointer <= 0;
        end else if (cs && wr_en && !full) begin
            fifo[write_pointer[FIFO_DEPTH_LOG-1:0]] <= data_in;
            write_pointer <= write_pointer + 1'b1;
        end
    end

    // Read operation
    always @(posedge clk or negedge rst_n) begin
        if (!rst_n) begin
            read_pointer <= 0;
            data_out <= 0;
        end else if (cs && rd_en && !empty) begin
            data_out <= fifo[read_pointer[FIFO_DEPTH_LOG-1:0]];
            read_pointer <= read_pointer + 1'b1;
        end
    end

    // Status flag logic
    assign empty = (read_pointer == write_pointer);
    assign full  = (write_pointer[FIFO_DEPTH_LOG]     != read_pointer[FIFO_DEPTH_LOG]) &&
                   (write_pointer[FIFO_DEPTH_LOG-1:0] == read_pointer[FIFO_DEPTH_LOG-1:0]);

endmodule

fifo_sync_tb.v
`timescale 1ns / 1ps
//////////////////////////////////////////////////////////////////////////////////
// Company: 
// Engineer: 
// 
// Create Date: 06/09/2025 07:03:51 PM
// Design Name: 
// Module Name: fifo_sync_tb
// Project Name: 
// Target Devices: 
// Tool Versions: 
// Description: 
// 
// Dependencies: 
// 
// Revision:
// Revision 0.01 - File Created
// Additional Comments:
// 
//////////////////////////////////////////////////////////////////////////////////


module fifo_sync_tb;

    // Parameters
    parameter FIFO_DEPTH = 8;
    parameter DATA_WIDTH = 32;

    // Testbench signals
    reg clk;
    reg rst_n;
    reg cs;
    reg wr_en;
    reg rd_en;
    reg [DATA_WIDTH-1:0] data_in;
    wire [DATA_WIDTH-1:0] data_out;
    wire empty;
    wire full;

    // Instantiate the FIFO
    fifo_sync #(
        .FIFO_DEPTH(FIFO_DEPTH),
        .DATA_WIDTH(DATA_WIDTH)
    ) dut (
        .clk(clk),
        .rst_n(rst_n),
        .cs(cs),
        .wr_en(wr_en),
        .rd_en(rd_en),
        .data_in(data_in),
        .data_out(data_out),
        .empty(empty),
        .full(full)
    );

    // Clock generation (10ns period)
    always #5 clk = ~clk;

    // Task to write data
    task fifo_write(input [DATA_WIDTH-1:0] data);
        begin
            @(posedge clk);
            if (!full) begin
                cs <= 1;
                wr_en <= 1;
                rd_en <= 0;
                data_in <= data;
            end
            @(posedge clk);
            cs <= 0;
            wr_en <= 0;
        end
    endtask

    // Task to read data
    task fifo_read;
        begin
            @(posedge clk);
            if (!empty) begin
                cs <= 1;
                wr_en <= 0;
                rd_en <= 1;
            end
            @(posedge clk);
            cs <= 0;
            rd_en <= 0;
        end
    endtask

    // Initial block
    initial begin
        // Enable waveform dump
        $dumpfile("fifo_sync_tb.vcd");
        $dumpvars(0, fifo_sync_tb);

        // Initialize
        clk = 0;
        rst_n = 0;
        cs = 0;
        wr_en = 0;
        rd_en = 0;
        data_in = 0;

        // Reset FIFO
        #10 rst_n = 1;

        // Write 8 data values into FIFO
        $display("Writing to FIFO...");
        repeat (FIFO_DEPTH) begin
            fifo_write($random);
        end

        // Try writing when full
        $display("Attempting write when FIFO is full...");
        fifo_write(32'hDEADBEEF);

        // Read 4 values from FIFO
        $display("Reading from FIFO...");
        repeat (4) begin
            fifo_read();
        end

        // Write 2 more values
        $display("Writing additional data...");
        fifo_write(32'hAABBCCDD);
        fifo_write(32'h11223344);

        // Read all values remaining in FIFO
        $display("Reading remaining values...");
        repeat (6) begin
            fifo_read();
        end

        // Try reading when empty
        $display("Attempting read when FIFO is empty...");
        fifo_read();

        // End simulation
        #20 $finish;
    end

endmodule

fifo_sync_tb.vcd
$date
   Mon Jun  9 19:04:48 2025
$end

$version
  2024.2.0
  $dumpfile ("fifo_sync_tb.vcd") 
$end

$timescale
  1ps
$end

$scope module fifo_sync_tb $end
$var reg 1 ! clk $end
$var reg 1 " rst_n $end
$var reg 1 # cs $end
$var reg 1 $ wr_en $end
$var reg 1 % rd_en $end
$var reg 32 & data_in [31:0] $end
$var wire 32 ' data_out [31:0] $end
$var wire 1 ( empty $end
$var wire 1 ) full $end
$scope module dut $end
$var wire 1 * clk $end
$var wire 1 + rst_n $end
$var wire 1 , cs $end
$var wire 1 - wr_en $end
$var wire 1 . rd_en $end
$var wire 32 / data_in [31:0] $end
$var reg 32 0 data_out [31:0] $end
$var wire 1 ( empty $end
$var wire 1 ) full $end
$var reg 4 1 write_pointer [3:0] $end
$var reg 4 2 read_pointer [3:0] $end
$upscope $end
$scope task fifo_write $end
$var reg 32 3 data [31:0] $end
$upscope $end
$scope task fifo_read $end
$upscope $end
$upscope $end
$enddefinitions $end

#0
$dumpvars
0!
0"
0#
0$
0%
b0 &
b0 '
1(
0)
0*
0+
0,
0-
0.
b0 /
b0 0
b0 1
b0 2
bx 3
$end

#5000
1!
1*

#10000
0!
1"
0*
1+
b10010000101010011010100100100 3

#15000
1!
1#
1$
b10010000101010011010100100100 &
1*
1,
1-
b10010000101010011010100100100 /

#20000
0!
0*

#25000
1!
0#
0$
0(
1*
0,
0-
b1 1
b11000000100010010101111010000001 3

#30000
0!
0*

#35000
1!
1#
1$
b11000000100010010101111010000001 &
1*
1,
1-
b11000000100010010101111010000001 /

#40000
0!
0*

#45000
1!
0#
0$
1*
0,
0-
b10 1
b10000100100001001101011000001001 3

#50000
0!
0*

#55000
1!
1#
1$
b10000100100001001101011000001001 &
1*
1,
1-
b10000100100001001101011000001001 /

#60000
0!
0*

#65000
1!
0#
0$
1*
0,
0-
b11 1
b10110001111100000101011001100011 3

#70000
0!
0*

#75000
1!
1#
1$
b10110001111100000101011001100011 &
1*
1,
1-
b10110001111100000101011001100011 /

#80000
0!
0*

#85000
1!
0#
0$
1*
0,
0-
b100 1
b110101110010111101100001101 3

#90000
0!
0*

#95000
1!
1#
1$
b110101110010111101100001101 &
1*
1,
1-
b110101110010111101100001101 /

#100000
0!
0*

#105000
1!
0#
0$
1*
0,
0-
b101 1
b1000110110111111001100110001101 3

#110000
0!
0*

#115000
1!
1#
1$
b1000110110111111001100110001101 &
1*
1,
1-
b1000110110111111001100110001101 /

#120000
0!
0*

#125000
1!
0#
0$
1*
0,
0-
b110 1
b10110010110000101000010001100101 3

#130000
0!
0*

#135000
1!
1#
1$
b10110010110000101000010001100101 &
1*
1,
1-
b10110010110000101000010001100101 /

#140000
0!
0*

#145000
1!
0#
0$
1*
0,
0-
b111 1
b10001001001101110101001000010010 3

#150000
0!
0*

#155000
1!
1#
1$
b10001001001101110101001000010010 &
1*
1,
1-
b10001001001101110101001000010010 /

#160000
0!
0*

#165000
1!
0#
0$
1)
1*
0,
0-
b1000 1
b11011110101011011011111011101111 3

#170000
0!
0*

#175000
1!
1*

#180000
0!
0*

#185000
1!
1*

#190000
0!
0*

#195000
1!
1#
1%
1*
1,
1.

#200000
0!
0*

#205000
1!
0#
0%
b10010000101010011010100100100 '
0)
1*
0,
0.
b10010000101010011010100100100 0
b1 2

#210000
0!
0*

#215000
1!
1#
1%
1*
1,
1.

#220000
0!
0*

#225000
1!
0#
0%
b11000000100010010101111010000001 '
1*
0,
0.
b11000000100010010101111010000001 0
b10 2

#230000
0!
0*

#235000
1!
1#
1%
1*
1,
1.

#240000
0!
0*

#245000
1!
0#
0%
b10000100100001001101011000001001 '
1*
0,
0.
b10000100100001001101011000001001 0
b11 2

#250000
0!
0*

#255000
1!
1#
1%
1*
1,
1.

#260000
0!
0*

#265000
1!
0#
0%
b10110001111100000101011001100011 '
1*
0,
0.
b10110001111100000101011001100011 0
b100 2
b10101010101110111100110011011101 3

#270000
0!
0*

#275000
1!
1#
1$
b10101010101110111100110011011101 &
1*
1,
1-
b10101010101110111100110011011101 /

#280000
0!
0*

#285000
1!
0#
0$
1*
0,
0-
b1001 1
b10001001000100011001101000100 3

#290000
0!
0*

#295000
1!
1#
1$
b10001001000100011001101000100 &
1*
1,
1-
b10001001000100011001101000100 /

#300000
0!
0*

#305000
1!
0#
0$
1*
0,
0-
b1010 1

#310000
0!
0*

#315000
1!
1#
1%
1*
1,
1.

#320000
0!
0*

#325000
1!
0#
0%
b110101110010111101100001101 '
1*
0,
0.
b110101110010111101100001101 0
b101 2

#330000
0!
0*

#335000
1!
1#
1%
1*
1,
1.

#340000
0!
0*

#345000
1!
0#
0%
b1000110110111111001100110001101 '
1*
0,
0.
b1000110110111111001100110001101 0
b110 2

#350000
0!
0*

#355000
1!
1#
1%
1*
1,
1.

#360000
0!
0*

#365000
1!
0#
0%
b10110010110000101000010001100101 '
1*
0,
0.
b10110010110000101000010001100101 0
b111 2

#370000
0!
0*

#375000
1!
1#
1%
1*
1,
1.

#380000
0!
0*

#385000
1!
0#
0%
b10001001001101110101001000010010 '
1*
0,
0.
b10001001001101110101001000010010 0
b1000 2

#390000
0!
0*

#395000
1!
1#
1%
1*
1,
1.

#400000
0!
0*

#405000
1!
0#
0%
b10101010101110111100110011011101 '
1*
0,
0.
b10101010101110111100110011011101 0
b1001 2

#410000
0!
0*

#415000
1!
1#
1%
1*
1,
1.

#420000
0!
0*

#425000
1!
0#
0%
b10001001000100011001101000100 '
1(
1*
0,
0.
b10001001000100011001101000100 0
b1010 2

